ETEC325Library/Algorithms.py
ETEC325Library/Functions.py
ETEC325Library/__init__.py
etec325library-1.0.0.dist-info/METADATA
etec325library-1.0.0.dist-info/WHEEL
etec325library-1.0.0.dist-info/licenses/COPYING
etec325library-1.0.0.dist-info/RECORD
