Metadata-Version: 2.4
Name: ETEC325Library
Version: 1.0.0
Summary: Library Functions for ETEC 325
Project-URL: Homepage, https://github.com/User10166/ETEC325Library
Project-URL: Issues, https://github.com/User10166/ETEC325Library/issues
Author-email: "R. Duke" <rduke01@nyit.edu>
License-Expression: GPL-3.0-only
License-File: COPYING
Classifier: Intended Audience :: Education
Classifier: License :: OSI Approved :: GNU General Public License v3 (GPLv3)
Classifier: Natural Language :: English
Classifier: Programming Language :: Python :: 3.9
Classifier: Programming Language :: Python :: 3.10
Classifier: Programming Language :: Python :: 3.11
Classifier: Topic :: Scientific/Engineering
Requires-Python: >=3.9
Requires-Dist: matplotlib
Requires-Dist: numpy
Requires-Dist: openpyxl
Requires-Dist: pandas
Requires-Dist: python-docx
Requires-Dist: scikit-learn
Requires-Dist: scipy
Requires-Dist: xlsxwriter
